libvirt_provider/__init__.py
libvirt_provider/_version.py
libvirt_provider/client.py
libvirt_provider/codes.py
libvirt_provider/config.py
libvirt_provider/defaults.py
libvirt_provider/models.py
libvirt_provider/pool.py
libvirt_provider/types.py
libvirt_provider/cli/__init__.py
libvirt_provider/cli/cli.py
libvirt_provider/cli/corc.py
libvirt_provider/cli/helpers.py
libvirt_provider/cli/input_groups/__init__.py
libvirt_provider/cli/input_groups/container.py
libvirt_provider/cli/input_groups/driver.py
libvirt_provider/cli/input_groups/instance.py
libvirt_provider/cli/parsers/__init__.py
libvirt_provider/cli/parsers/actions.py
libvirt_provider/cli/parsers/container.py
libvirt_provider/cli/parsers/driver.py
libvirt_provider/cli/parsers/instance.py
libvirt_provider/container/__init__.py
libvirt_provider/container/create.py
libvirt_provider/container/get.py
libvirt_provider/container/ls.py
libvirt_provider/container/remove.py
libvirt_provider/container/stop.py
libvirt_provider/instance/__init__.py
libvirt_provider/instance/create.py
libvirt_provider/instance/get.py
libvirt_provider/instance/ls.py
libvirt_provider/instance/purge.py
libvirt_provider/instance/remove.py
libvirt_provider/instance/show.py
libvirt_provider/instance/start.py
libvirt_provider/instance/state.py
libvirt_provider/instance/stop.py
libvirt_provider/utils/__init__.py
libvirt_provider/utils/db.py
libvirt_provider/utils/format.py
libvirt_provider/utils/io.py
libvirt_provider/utils/user.py
tests/__init__.py
tests/context.py
tests/test_cli_base.py
tests/test_cli_libvirt.py
tests/test_dummy.py
tests/test_dummy_pool.py
tests/smoke/__init__.py
tests/smoke/test_libvirt.py
tests/smoke/test_libvirt_pool.py
tests/smoke/test_libvirt_remote_node.py
tests/smoke/utils/__init__.py
tests/smoke/utils/job.py
libvirt_provider-0.0.3.dist-info/LICENSE
libvirt_provider-0.0.3.dist-info/METADATA
libvirt_provider-0.0.3.dist-info/WHEEL
libvirt_provider-0.0.3.dist-info/entry_points.txt
libvirt_provider-0.0.3.dist-info/top_level.txt
libvirt_provider-0.0.3.dist-info/RECORD
