Metadata-Version: 2.2
Name: libvirt_provider
Version: 0.0.3
Summary: A corc plugin for a libvirt orchestration provider
Home-page: https://github.com/rasmunk/libvirt_provider
Author: Rasmus Munk
Author-email: munk1@live.dk
License: GNU General Public License v2 (GPLv2)
Keywords: Orchstration,Virtual Machine
Classifier: Intended Audience :: Developers
Classifier: Intended Audience :: System Administrators
Classifier: License :: OSI Approved :: GNU General Public License v2 (GPLv2)
Classifier: Programming Language :: Python
Classifier: Programming Language :: Python :: 3.8
Classifier: Programming Language :: Python :: 3.9
Classifier: Programming Language :: Python :: 3.10
Classifier: Programming Language :: Python :: 3.11
Classifier: Programming Language :: Python :: 3.12
License-File: LICENSE
Requires-Dist: libvirt-python>=9.9.0
Requires-Dist: jinja2>=3.1.3
Requires-Dist: PyYAML>=6.0.1
Provides-Extra: test
Requires-Dist: pytest>=7.2.1; extra == "test"
Requires-Dist: wget>=3.2; extra == "test"
Requires-Dist: deling>=0.2.4; extra == "test"
Requires-Dist: gen-vm-image>=0.0.0a0; extra == "test"
Requires-Dist: rstcheck==6.2.4; extra == "test"
Provides-Extra: dev
Requires-Dist: flake8==6.1.0; extra == "dev"
Requires-Dist: black==24.3.0; extra == "dev"
Requires-Dist: rstcheck==6.2.4; extra == "dev"
Dynamic: author
Dynamic: author-email
Dynamic: classifier
Dynamic: description
Dynamic: description-content-type
Dynamic: home-page
Dynamic: keywords
Dynamic: license
Dynamic: provides-extra
Dynamic: requires-dist
Dynamic: summary
